sasconnect/sasapi.py
sasconnect/sastest.py
sasconnect-3.0.dist-info/LICENSE
sasconnect-3.0.dist-info/METADATA
sasconnect-3.0.dist-info/WHEEL
sasconnect-3.0.dist-info/top_level.txt
sasconnect-3.0.dist-info/RECORD
