Metadata-Version: 2.1
Name: sasconnect
Version: 3.0
Summary: Python SDK for API users
Home-page: https://zebull.in
Author: Pradeep
Author-email: pradeep@stoneagesolutions.com
License: MIT
Platform: UNKNOWN
Classifier: License :: OSI Approved :: MIT License
Classifier: Programming Language :: Python :: 3.9
Classifier: Operating System :: OS Independent
Classifier: Natural Language :: English
Classifier: Intended Audience :: Developers
Requires-Dist: requests
